Metadata-Version: 2.1
Name: some-hoes
Version: 0.0.1
Summary: It counts your bitches
Author: Pingitzer David
License-File: license.txt
